django_nexus_auth-0.1.7.dist-info/licenses/LICENSE
nexus_auth/__init__.py
nexus_auth/apps.py
nexus_auth/exceptions.py
nexus_auth/serializers.py
nexus_auth/settings.py
nexus_auth/urls.py
nexus_auth/utils.py
nexus_auth/views.py
nexus_auth/providers/__init__.py
nexus_auth/providers/base.py
nexus_auth/providers/factory.py
nexus_auth/providers/google.py
nexus_auth/providers/microsoft.py
django_nexus_auth-0.1.7.dist-info/METADATA
django_nexus_auth-0.1.7.dist-info/WHEEL
django_nexus_auth-0.1.7.dist-info/top_level.txt
django_nexus_auth-0.1.7.dist-info/RECORD
