Metadata-Version: 2.4
Name: django-nexus-auth
Version: 0.1.7
Summary: OIDC Authentication for Django REST Framework with JWT support
Home-page: https://github.com/panevo/django-nexus-auth
Author: Gabriel Tan
Author-email: gabriel.tan@panevo.com
Classifier: Development Status :: 3 - Alpha
Classifier: Framework :: Django
Classifier: Intended Audience :: Developers
Classifier: Programming Language :: Python :: 3
Classifier: Topic :: Software Development :: Libraries :: Python Modules
License-File: LICENSE
Requires-Dist: Django>=4.2.19
Requires-Dist: djangorestframework>=3.14.0
Requires-Dist: djangorestframework-simplejwt>=5.4.0
Dynamic: author
Dynamic: author-email
Dynamic: classifier
Dynamic: description
Dynamic: description-content-type
Dynamic: home-page
Dynamic: license-file
Dynamic: requires-dist
Dynamic: summary
